climush/__init__.py
climush/binfo_old.py
climush/bioinfo.py
climush/config.py
climush/constants.py
climush/mapping.py
climush/utilities.py
climush/viz.py
climush-0.0.8.dist-info/METADATA
climush-0.0.8.dist-info/WHEEL
climush-0.0.8.dist-info/top_level.txt
climush-0.0.8.dist-info/RECORD
