Metadata-Version: 2.1
Name: climush
Version: 0.0.8
Summary: Tools to run the CliMush bioinformatics pipeline.
Author-email: Carolyn Delevich <cdelevic@uoregon.edu>
Project-URL: Homepage, https://github.com/cdelevich/climush/tree/main/bioinformatics-pipeline
Project-URL: Repository, https://github.com/cdelevich/climush/tree/main/bioinformatics-pipeline/climush_py-package
Project-URL: Issues, https://github.com/cdelevich/climush/issues
Classifier: Programming Language :: Python :: 3
Classifier: License :: OSI Approved :: MIT License
Classifier: Development Status :: 3 - Alpha
Classifier: Topic :: Scientific/Engineering :: Bio-Informatics
Requires-Python: >=3.10
Requires-Dist: pandas
Requires-Dist: scipy
Requires-Dist: numpy
Requires-Dist: matplotlib
Requires-Dist: seaborn
Requires-Dist: Bio
Requires-Dist: tomlkit
